anit/__init__.py
anit/tests.py
anit-0.0.10.data/scripts/anit
anit-0.0.10.dist-info/METADATA
anit-0.0.10.dist-info/WHEEL
anit-0.0.10.dist-info/top_level.txt
anit-0.0.10.dist-info/RECORD
