Metadata-Version: 2.1
Name: anit
Version: 0.0.10
Summary: May the force be with you.
Home-page: UNKNOWN
Author: Animite Software Foundation
Author-email: shaurya.p.singh21@gmail.com
License: UNKNOWN
Platform: UNKNOWN
Requires-Dist: yagmail
Requires-Dist: pyfiglet
Requires-Dist: click
